jelapi/__init__.py
jelapi/connector.py
jelapi/exceptions.py
jelapi/factories.py
jelapi/__pycache__/__init__.cpython-39.pyc
jelapi/__pycache__/connector.cpython-39.pyc
jelapi/__pycache__/exceptions.cpython-39.pyc
jelapi/__pycache__/factories.cpython-39.pyc
jelapi/classes/__init__.py
jelapi/classes/_volume.py
jelapi/classes/environment.py
jelapi/classes/group.py
jelapi/classes/jelasticobject.py
jelapi/classes/mountpoint.py
jelapi/classes/node.py
jelapi/classes/nodegroup.py
jelapi/classes/__pycache__/__init__.cpython-39.pyc
jelapi/classes/__pycache__/_volume.cpython-39.pyc
jelapi/classes/__pycache__/environment.cpython-39.pyc
jelapi/classes/__pycache__/group.cpython-39.pyc
jelapi/classes/__pycache__/jelasticobject.cpython-39.pyc
jelapi/classes/__pycache__/mountpoint.cpython-39.pyc
jelapi/classes/__pycache__/node.cpython-39.pyc
jelapi/classes/__pycache__/nodegroup.cpython-39.pyc
tests/__init__.py
tests/test_connector.py
tests/test_envgroup.py
tests/test_globalconfig.py
tests/test_jelenvironment.py
tests/test_jelnode.py
tests/test_jelnodegroup.py
tests/test_jelobjects.py
tests/test_mountpoint.py
tests/test_volume.py
tests/utils.py
tests/__pycache__/__init__.cpython-39-pytest-6.2.2.pyc
tests/__pycache__/test_connector.cpython-39-pytest-6.2.2.pyc
tests/__pycache__/test_envgroup.cpython-39-pytest-6.2.2.pyc
tests/__pycache__/test_globalconfig.cpython-39-pytest-6.2.2.pyc
tests/__pycache__/test_jelenvironment.cpython-39-pytest-6.2.2.pyc
tests/__pycache__/test_jelnode.cpython-39-pytest-6.2.2.pyc
tests/__pycache__/test_jelnodegroup.cpython-39-pytest-6.2.2.pyc
tests/__pycache__/test_jelobjects.cpython-39-pytest-6.2.2.pyc
tests/__pycache__/test_mountpoint.cpython-39-pytest-6.2.2.pyc
tests/__pycache__/test_volume.cpython-39-pytest-6.2.2.pyc
tests/__pycache__/utils.cpython-39-pytest-6.2.2.pyc
jelapi-0.1.1.dist-info/LICENSE
jelapi-0.1.1.dist-info/METADATA
jelapi-0.1.1.dist-info/WHEEL
jelapi-0.1.1.dist-info/top_level.txt
jelapi-0.1.1.dist-info/RECORD
