Metadata-Version: 2.1
Name: jelapi
Version: 0.1.1
Summary: jelapi: A Jelastic API Python library
Home-page: https://github.com/liip/jelapi
Author: Didier Raboud
Author-email: didier.raboud@liip.ch
License: GPLv3+
Platform: UNKNOWN
Classifier: Programming Language :: Python :: 3
Classifier: Programming Language :: Python :: 3.7
Classifier: Programming Language :: Python :: 3.8
Classifier: Programming Language :: Python :: 3.9
Classifier: License :: OSI Approved :: GNU General Public License v3 or later (GPLv3+)
Classifier: Operating System :: OS Independent
Classifier: Intended Audience :: Developers
Classifier: Intended Audience :: System Administrators
Classifier: Topic :: Software Development :: Libraries
Classifier: Development Status :: 4 - Beta
Requires-Python: >=3.7
Requires-Dist: httpx[http2] (>=0.18)
Provides-Extra: test
Requires-Dist: factory-boy ; extra == 'test'
Requires-Dist: faker-enum ; extra == 'test'
Requires-Dist: pytest-cov ; extra == 'test'
Requires-Dist: respx (>=0.17) ; extra == 'test'
